setup.py
tskv/__init__.py
tskv/tskv.py
tskv/version.py
tskv.egg-info/PKG-INFO
tskv.egg-info/SOURCES.txt
tskv.egg-info/dependency_links.txt
tskv.egg-info/top_level.txt